nmc_met_graphics/__init__.py
nmc_met_graphics/animate.py
nmc_met_graphics/mask.py
nmc_met_graphics/util.py
nmc_met_graphics/cmap/__init__.py
nmc_met_graphics/cmap/cm.py
nmc_met_graphics/cmap/cm_bb.py
nmc_met_graphics/cmap/cpt.py
nmc_met_graphics/cmap/ctables.py
nmc_met_graphics/cmap/wrf.py
nmc_met_graphics/magics/__init__.py
nmc_met_graphics/magics/common.py
nmc_met_graphics/magics/dynamics.py
nmc_met_graphics/magics/efi.py
nmc_met_graphics/magics/map_set.py
nmc_met_graphics/magics/moisture.py
nmc_met_graphics/magics/pv.py
nmc_met_graphics/magics/qpf.py
nmc_met_graphics/magics/thermal.py
nmc_met_graphics/magics/util.py
nmc_met_graphics/magics/maps/__init__.py
nmc_met_graphics/magics/maps/moisture.py
nmc_met_graphics/magics/maps/util.py
nmc_met_graphics/maps/__init__.py
nmc_met_graphics/maps/moisture.py
nmc_met_graphics/maps/util.py
nmc_met_graphics/plot/__init__.py
nmc_met_graphics/plot/calmap.py
nmc_met_graphics/plot/cartopy_scalebar.py
nmc_met_graphics/plot/china_map.py
nmc_met_graphics/plot/cldas.py
nmc_met_graphics/plot/mapview.py
nmc_met_graphics/plot/misc.py
nmc_met_graphics/plot/olympic.py
nmc_met_graphics/plot/precipitation.py
nmc_met_graphics/plot/synoptic.py
nmc_met_graphics/plot/tcmarkers.py
nmc_met_graphics/plot/util.py
nmc_met_graphics/plot/verify.py
nmc_met_graphics/resources/__init__.py
nmc_met_graphics/resources/datasets.py
nmc_met_graphics/resources/mplstyle.py
nmc_met_graphics/resources/.ipynb_checkpoints/datasets-checkpoint.py
nmc_met_graphics/resources/colormaps_cmasher/cm_amber.txt
nmc_met_graphics/resources/colormaps_cmasher/cm_amethyst.txt
nmc_met_graphics/resources/colormaps_cmasher/cm_apple.txt
nmc_met_graphics/resources/colormaps_cmasher/cm_arctic.txt
nmc_met_graphics/resources/colormaps_cmasher/cm_bubblegum.txt
nmc_met_graphics/resources/colormaps_cmasher/cm_chroma.txt
nmc_met_graphics/resources/colormaps_cmasher/cm_copper.txt
nmc_met_graphics/resources/colormaps_cmasher/cm_cosmic.txt
nmc_met_graphics-0.2.0.dist-info/licenses/LICENSE
nmc_met_graphics-0.2.0.dist-info/METADATA
nmc_met_graphics-0.2.0.dist-info/WHEEL
nmc_met_graphics-0.2.0.dist-info/top_level.txt
nmc_met_graphics-0.2.0.dist-info/RECORD
